studentcomplaintlib/__init__.py
studentcomplaintlib/post_complaint.py
studentcomplaintlib-0.2.0.dist-info/LICENSE
studentcomplaintlib-0.2.0.dist-info/METADATA
studentcomplaintlib-0.2.0.dist-info/WHEEL
studentcomplaintlib-0.2.0.dist-info/top_level.txt
studentcomplaintlib-0.2.0.dist-info/RECORD
