Metadata-Version: 2.2
Name: studentcomplaintlib
Version: 0.2.0
Summary: This is a simple message for complaint posting.
Home-page: 
Author: Rohith
Author-email: x23411520@student.ncirl.ie
Keywords: studentcomplaintlib
Classifier: Intended Audience :: Education
Classifier: Operating System :: Microsoft :: Windows :: Windows 10
Classifier: License :: OSI Approved :: MIT License
Classifier: Programming Language :: Python :: 3
Requires-Python: >=3.6
License-File: LICENSE
Dynamic: author
Dynamic: author-email
Dynamic: classifier
Dynamic: description
Dynamic: keywords
Dynamic: requires-python
Dynamic: summary
